jacobi_poly/__init__.py
jacobi_poly/__main__.py
jacobi_poly/_lgamma.py
jacobi_poly/_main.py
jacobi_poly/_triplet.py
jacobi_poly/cli.py
jacobi_poly/py.typed
jacobi_poly-1.0.6.dist-info/licenses/LICENSE
jacobi_poly-1.0.6.dist-info/METADATA
jacobi_poly-1.0.6.dist-info/WHEEL
jacobi_poly-1.0.6.dist-info/entry_points.txt
jacobi_poly-1.0.6.dist-info/top_level.txt
jacobi_poly-1.0.6.dist-info/RECORD
