Metadata-Version: 2.4
Name: jacobi-poly
Version: 1.0.6
Summary: Compute Jacobi polynomial from order 0 to N efficiently in NumPy / PyTorch / JAX / array API
Author-email: 34j <34j.95a2p@simplelogin.com>
License: MIT
Project-URL: Bug Tracker, https://github.com/34j/jacobi-poly/issues
Project-URL: Changelog, https://github.com/34j/jacobi-poly/blob/main/CHANGELOG.md
Project-URL: documentation, https://jacobi-poly.readthedocs.io
Project-URL: repository, https://github.com/34j/jacobi-poly
Classifier: Development Status :: 2 - Pre-Alpha
Classifier: Intended Audience :: Developers
Classifier: Natural Language :: English
Classifier: Operating System :: OS Independent
Classifier: Programming Language :: Python :: 3.9
Classifier: Programming Language :: Python :: 3.10
Classifier: Programming Language :: Python :: 3.11
Classifier: Programming Language :: Python :: 3.12
Classifier: Programming Language :: Python :: 3.13
Classifier: Topic :: Software Development :: Libraries
Requires-Python: >=3.12
License-File: LICENSE
Requires-Dist: array-api-compat>=1.13.0
Requires-Dist: array-api-extra>=0.9.2
Requires-Dist: numba>=0.63.0
Requires-Dist: numpy>=2.3.5
Requires-Dist: rich>=14.2.0
Requires-Dist: scipy>=1.16.3
Requires-Dist: typer>=0.21.0
Requires-Dist: types-array-api>=1.2.0
Provides-Extra: triplet
Requires-Dist: py3nj>=0.2.1; extra == "triplet"
Dynamic: license-file
